MANIFEST.in
README.rst
setup.py
docs/HISTORY.txt
docs/LICENSE.GPL
docs/LICENSE.txt
ftw/__init__.py
ftw.catalogdoctor.egg-info/PKG-INFO
ftw.catalogdoctor.egg-info/SOURCES.txt
ftw.catalogdoctor.egg-info/dependency_links.txt
ftw.catalogdoctor.egg-info/entry_points.txt
ftw.catalogdoctor.egg-info/namespace_packages.txt
ftw.catalogdoctor.egg-info/not-zip-safe
ftw.catalogdoctor.egg-info/requires.txt
ftw.catalogdoctor.egg-info/top_level.txt
ftw/catalogdoctor/__init__.py
ftw/catalogdoctor/command.py
ftw/catalogdoctor/compat.py
ftw/catalogdoctor/configure.zcml
ftw/catalogdoctor/debug.py
ftw/catalogdoctor/exceptions.py
ftw/catalogdoctor/healthcheck.py
ftw/catalogdoctor/scheduler.py
ftw/catalogdoctor/surgery.py
ftw/catalogdoctor/testing.py
ftw/catalogdoctor/utils.py
ftw/catalogdoctor/tests/__init__.py
ftw/catalogdoctor/tests/test_catalog_healthcheck.py
ftw/catalogdoctor/tests/test_command.py
ftw/catalogdoctor/tests/test_debug.py
ftw/catalogdoctor/tests/test_selftest.py
ftw/catalogdoctor/tests/test_surgery.py
ftw/catalogdoctor/tests/test_surgery_remove_from_boolean_index.py
ftw/catalogdoctor/tests/test_surgery_remove_from_date_range_index.py
ftw/catalogdoctor/tests/test_surgery_remove_from_extended_path_index.py
ftw/catalogdoctor/tests/test_surgery_remove_from_unindex.py
ftw/catalogdoctor/tests/test_surgery_remove_from_uuidindex.py
ftw/catalogdoctor/tests/test_surgery_unindex_object.py
ftw/catalogdoctor/tests/test_utils.py